django_static_converter/__init__.py
django_static_converter/converter.py
django_static_converter/management/__init__.py
django_static_converter/management/commands/__init__.py
django_static_converter/management/commands/convert-static.py
django_static_converter-1.0.3.dist-info/METADATA
django_static_converter-1.0.3.dist-info/WHEEL
django_static_converter-1.0.3.dist-info/top_level.txt
django_static_converter-1.0.3.dist-info/RECORD
