Metadata-Version: 2.1
Name: django-static-converter
Version: 1.0.3
Summary: A Django package that automatically converts src and href attributes in HTML templates to Django's static template tags, making it easier to manage static files efficiently.
Home-page: https://github.com/pezhman-najafie, https://github.com/sahel-shiravand 
Author: Pezhman Najafi, Sahel Shiravand
Author-email: pezhman3500@gmail.com, sahelshiravand@yahoo.com
License: UNKNOWN
Platform: UNKNOWN
Classifier: Framework :: Django
Classifier: Programming Language :: Python :: 3
Classifier: License :: OSI Approved :: MIT License
Classifier: Operating System :: OS Independent
Requires-Python: >=3.6
Requires-Dist: beautifulsoup4
